{
  "tasks": {
    "dev": "deno task dev:api & deno task dev:vite",
    "dev:api": "deno run --allow-env --allow-net --allow-read api/main.ts",
    "dev:vite": "deno run -A npm:vite",
    "build": "deno run -A npm:vite build",
    "serve": {
      "command": "deno task dev:api",
      "description": "Run the build, and then start the API server",
      "dependencies": [
        "deno task build"
      ]
    }
  },
  "imports": {
    "@bearz/dotenv": "jsr:@std/dotenv@^0.225.3",
    "@hono/hono": "jsr:@hono/hono@^4.6.15",
    "@solidjs/router": "npm:@solidjs/router@^0.14.10",
    "@std/dotenv": "jsr:@std/dotenv@^0.225.3",
    "@types/pg": "npm:@types/pg@^8.11.10",
    "drizzle-kit": "npm:drizzle-kit@^0.30.1",
    "drizzle-orm": "npm:drizzle-orm@^0.38.3",
    "pg": "npm:pg@^8.13.1"
  },
  "compilerOptions": {
    "jsx": "react-jsx",
    "jsxImportSource": "solid-js",
    "lib": [
      "DOM",
      "DOM.Iterable",
      "ESNext"
    ]
  }
}
